briar_repl/__init__.py
briar_repl/__main__.py
briar_repl/blogs.py
briar_repl/connections.py
briar_repl/contacts.py
briar_repl/messages.py
briar_repl/network.py
briar_repl/repl.py
briar_repl/start_up.py
briar_repl-21.2.20.dist-info/LICENSE
briar_repl-21.2.20.dist-info/WHEEL
briar_repl-21.2.20.dist-info/METADATA
briar_repl-21.2.20.dist-info/RECORD
