Metadata-Version: 2.1
Name: briar_repl
Version: 21.2.20
Summary: briar cli-messenger for briar:headless
Home-page: https://code.briarproject.org/fphemeral/briar_repl
License: UNKNOWN
Author: fphemeral
Author-email: fphemeral@i2pmail.org
Requires-Python: >=3.7
Classifier: License :: OSI Approved :: GNU General Public License v3 or later (GPLv3+)
Requires-Dist: colorful>=0.5.4
Requires-Dist: prompt-toolkit>=3.0.14
Requires-Dist: httpx>=0.16.1
Requires-Dist: websockets>=8.1.0
Requires-Dist: psutil>=5.8.0
